beads_mcp/__init__.py
beads_mcp/__main__.py
beads_mcp/bd_client.py
beads_mcp/bd_daemon_client.py
beads_mcp/config.py
beads_mcp/models.py
beads_mcp/py.typed
beads_mcp/server.py
beads_mcp/tools.py
beads_mcp-0.49.3.dist-info/METADATA
beads_mcp-0.49.3.dist-info/WHEEL
beads_mcp-0.49.3.dist-info/entry_points.txt
beads_mcp-0.49.3.dist-info/licenses/LICENSE
beads_mcp-0.49.3.dist-info/RECORD
