Metadata-Version: 2.4
Name: beads-mcp
Version: 0.49.3
Summary: MCP server for beads issue tracker.
Project-URL: Homepage, https://github.com/steveyegge/beads
Project-URL: Repository, https://github.com/steveyegge/beads
Project-URL: Documentation, https://github.com/steveyegge/beads/blob/main/integrations/beads-mcp/README.md
Project-URL: Issues, https://github.com/steveyegge/beads/issues
Author: Beads Contributors
Maintainer: Beads Contributors
License: MIT
License-File: LICENSE
Keywords: ai-agent,beads,claude,issue-tracker,mcp,model-context-protocol
Classifier: Development Status :: 3 - Alpha
Classifier: Intended Audience :: Developers
Classifier: License :: OSI Approved :: MIT License
Classifier: Programming Language :: Python :: 3
Classifier: Programming Language :: Python :: 3.10
Classifier: Programming Language :: Python :: 3.11
Classifier: Programming Language :: Python :: 3.12
Classifier: Programming Language :: Python :: 3.13
Classifier: Topic :: Software Development :: Bug Tracking
Classifier: Topic :: Software Development :: Libraries :: Python Modules
Requires-Python: >=3.10
Requires-Dist: fastmcp==2.14.4
Requires-Dist: pydantic-settings==2.12.0
Requires-Dist: pydantic==2.12.5
